beetsplug/autofix/__init__.py
beetsplug/autofix/about.py
beetsplug/autofix/command.py
beetsplug/autofix/common.py
beetsplug/autofix/config_default.yml
beetsplug/autofix/task/__init__.py
beetsplug/autofix/task/ab_data_fetcher.py
beetsplug/autofix/task/audio_conversion.py
beetsplug/autofix/task/genre_finder.py
beetsplug/autofix/task/missing_file_checker.py
beetsplug/autofix/task/tag_cleaner.py
beetsplug/autofix/task/xtractor.py
beetsplug/autofix/task/year_fixer.py
beets_autofix-0.1.6.dist-info/LICENSE.txt
beets_autofix-0.1.6.dist-info/METADATA
beets_autofix-0.1.6.dist-info/WHEEL
beets_autofix-0.1.6.dist-info/top_level.txt
beets_autofix-0.1.6.dist-info/RECORD
